sportident.py
sportident-1.2.8.dist-info/LICENSE
sportident-1.2.8.dist-info/METADATA
sportident-1.2.8.dist-info/WHEEL
sportident-1.2.8.dist-info/RECORD
