Metadata-Version: 2.1
Name: sportident
Version: 1.2.8
Summary: Python module to communicate with SportIdent main stations
Home-page: https://github.com/sportorg/sireader
License: GPLv3+
Keywords: sportident,orienteering,sportorg
Author: Danil Akhtarov
Author-email: daxartio@gmail.com
Requires-Python: >=3.8.1,<4.0.0
Classifier: License :: Other/Proprietary License
Classifier: Programming Language :: Python :: 3
Classifier: Programming Language :: Python :: 3.9
Classifier: Programming Language :: Python :: 3.10
Classifier: Programming Language :: Python :: 3.11
Classifier: Programming Language :: Python :: 3.12
Requires-Dist: pyserial
Requires-Dist: six
Project-URL: Changelog, https://github.com/sportorg/sireader/blob/main/CHANGELOG.md/
Project-URL: Repository, https://github.com/sportorg/sireader
